pyappcreator/__init__.py
pyappcreator/buffer.py
pyappcreator/component.py
pyappcreator/consts.py
pyappcreator/engine.py
pyappcreator/graphic.py
pyappcreator/mgr_image.py
pyappcreator/utils.py
pyappcreator-1.0.2.dist-info/METADATA
pyappcreator-1.0.2.dist-info/WHEEL
pyappcreator-1.0.2.dist-info/top_level.txt
pyappcreator-1.0.2.dist-info/RECORD
