Metadata-Version: 2.1
Name: pyappcreator
Version: 1.0.2
Summary: Python Application Creator
Home-page: https://cnb.cool/baozilaji/pyappcreator
Author: baozilaji
Author-email: baozilaji@gmail.com
License: UNKNOWN
Platform: UNKNOWN
Requires-Python: >=3.9
Requires-Dist: pillow (==11.2.1)
Requires-Dist: requests (==2.28.2)
